setup.py
ratchet/__init__.py
ratchet.egg-info/PKG-INFO
ratchet.egg-info/SOURCES.txt
ratchet.egg-info/dependency_links.txt
ratchet.egg-info/entry_points.txt
ratchet.egg-info/requires.txt
ratchet.egg-info/top_level.txt
ratchet/contrib/__init__.py
ratchet/contrib/django/__init__.py
ratchet/contrib/django/context_processors.py
ratchet/contrib/django/middleware.py
ratchet/contrib/django/models.py
ratchet/contrib/django/tests.py
ratchet/contrib/pyramid/__init__.py